server_check/__init__.py
server_check/common.py
server_check/run_checks.py
server_check/checks/__init__.py
server_check/checks/backup_age.py
server_check/checks/base.py
server_check/checks/dyndns.py
server_check/checks/mail.py
server_check/checks/time_difference.py
nose_server_check-1.1.0.dist-info/METADATA
nose_server_check-1.1.0.dist-info/WHEEL
nose_server_check-1.1.0.dist-info/entry_points.txt
nose_server_check-1.1.0.dist-info/top_level.txt
nose_server_check-1.1.0.dist-info/RECORD
