Metadata-Version: 2.1
Name: nose-server-check
Version: 1.1.0
Summary: Check functions of a server
Author: Seuling N.
License: Apache License 2.0
Requires-Python: >=3.10
Requires-Dist: requests ~=2.31
Requires-Dist: multi-notifier ~=0.2.0
